[
    {
        "title": "Главная",
        "path": "/dashboard",
        "type": "tab",
        "icon": "grades",
        "keepAlive": false
    },
    {
        "title": "Управление товарами",
        "path": "/products",
        "type": "tab",
        "icon": "certificate",
        "keepAlive": false
    },
    {
        "title": "Виртуальный склад",
        "path": "/werehouse",
        "type": "tab",
        "icon": "certificate",
        "keepAlive": false
    },
    {
        "title": "Заказы",
        "path": "/orders",
        "type": "tab",
        "icon": "ranking",
        "keepAlive": false
    },
    {
        "title": "Обучение",
        "path": "/learning",
        "type": "tab",
        "icon": "ranking",
        "keepAlive": false
    }
]
